{
  "id": "667c137a15854a0b085cd700",
  "metadata": {
    "id": "667c137a15854a0b085cd700",
    "slug": "request-a-form",
    "title": "Request a form",
    "organisation": "Defra",
    "teamName": "Defra Forms team",
    "teamEmail": "defraforms@defra.gov.uk",
    "contact": {
      "email": {
        "address": "defraforms@defra.gov.uk",
        "responseTime": "We aim to respond as soon as possible."
      }
    },
    "submissionGuidance": "The Defra Forms team aim to respond to you within 5 working days.",
    "privacyNoticeUrl": "https://defra.sharepoint.com/sites/Community4442/SitePages/Privacy-notice--Defra-Forms.aspx",
    "notificationEmail": "defraforms@defra.gov.uk",
    "draft": {
      "updatedAt": "2024-10-21T08:25:07.954Z",
      "updatedBy": {
        "id": "2cc8c6f5-89b3-4ab3-9eb7-6de798c287b7",
        "displayName": "Steven Thomas"
      },
      "createdAt": "2024-10-21T08:25:07.954Z",
      "createdBy": {
        "id": "2cc8c6f5-89b3-4ab3-9eb7-6de798c287b7",
        "displayName": "Steven Thomas"
      }
    },
    "live": {
      "updatedAt": "2024-10-10T16:57:53.970Z",
      "updatedBy": {
        "id": "7242070b-6d85-41fd-ade7-b34500bea1e9",
        "displayName": "Alex Luckett"
      },
      "createdAt": "2024-06-26T13:14:02.442Z",
      "createdBy": {
        "id": "aHrV2SevsVeAXXwItg1FX_w5RwaTvcwiJm-LtCBjN3s",
        "displayName": "Steven Thomas"
      }
    },
    "createdBy": {
      "id": "aHrV2SevsVeAXXwItg1FX_w5RwaTvcwiJm-LtCBjN3s",
      "displayName": "Steven Thomas"
    },
    "createdAt": "2024-06-26T13:14:02.442Z",
    "updatedBy": {
      "id": "2cc8c6f5-89b3-4ab3-9eb7-6de798c287b7",
      "displayName": "Steven Thomas"
    },
    "updatedAt": "2024-10-21T08:25:07.954Z"
  },
  "draft": {
    "name": "Request a form",
    "pages": [
      {
        "path": "/what-is-your-name",
        "title": "What is your name?",
        "components": [
          {
            "type": "TextField",
            "name": "textField",
            "title": "Name",
            "hint": "",
            "options": {},
            "schema": {}
          }
        ],
        "next": [
          {
            "path": "/what-is-your-email-address"
          }
        ]
      },
      {
        "title": "Summary",
        "path": "/summary",
        "controller": "./pages/summary.js",
        "components": [],
        "next": []
      },
      {
        "path": "/what-is-your-email-address",
        "title": "What is your email address?",
        "components": [
          {
            "name": "jwIhMa",
            "options": {},
            "schema": {},
            "type": "EmailAddressField",
            "title": "Email address"
          }
        ],
        "next": [
          {
            "path": "/will-you-be-the-owner-of-the-form"
          }
        ]
      },
      {
        "path": "/who-do-you-work-for",
        "title": "Who do you work for?",
        "components": [
          {
            "name": "NzsYde",
            "options": {},
            "schema": {},
            "type": "RadiosField",
            "title": "Your organisation",
            "list": "hqocBW",
            "values": {
              "type": "listRef"
            }
          }
        ],
        "next": [
          {
            "path": "/give-a-brief-description-of-your-service"
          }
        ]
      },
      {
        "path": "/give-a-brief-description-of-your-service",
        "title": "Give a brief description of your service",
        "components": [
          {
            "name": "drGlJl",
            "options": {},
            "schema": {},
            "type": "MultilineTextField",
            "title": "Description of your service"
          }
        ],
        "next": [
          {
            "path": "/do-you-have-an-existing-form"
          }
        ]
      },
      {
        "path": "/do-you-have-an-existing-form",
        "title": "Do you have an existing form?",
        "components": [
          {
            "name": "mCZCyf",
            "options": {},
            "schema": {},
            "type": "YesNoField",
            "title": "Existing form",
            "hint": "This can be an existing paper-based form, for example, a PDF or Microsoft Word document"
          }
        ],
        "next": [
          {
            "path": "/what-is-the-link-to-the-form-IyRbdG",
            "condition": "DkjIaR"
          },
          {
            "path": "/how-many-submissions-do-you-expect-to-receive-a-year"
          }
        ]
      },
      {
        "path": "/what-is-the-link-to-the-form-IyRbdG",
        "title": "What is the link to the form?",
        "components": [
          {
            "name": "ssTfVS",
            "options": {},
            "schema": {},
            "type": "TextField",
            "title": "Link for existing form"
          }
        ],
        "next": [
          {
            "path": "/is-your-form-updated-frequently"
          }
        ]
      },
      {
        "path": "/how-many-submissions-do-you-expect-to-receive-a-year",
        "title": "How many submissions do you expect to receive a year?",
        "components": [
          {
            "name": "IeDmsh",
            "options": {},
            "schema": {},
            "type": "RadiosField",
            "hint": "This will help us to provide you with a solution that meets your requirements",
            "title": "Number of annual applications",
            "list": "UEnuwn"
          }
        ],
        "next": [
          {
            "path": "/where-to-send-form-submissions"
          }
        ]
      },
      {
        "path": "/do-you-need-to-collect-a-payment",
        "title": "Do you need to collect a payment?",
        "components": [
          {
            "name": "AAWpzq",
            "options": {},
            "schema": {},
            "type": "YesNoField",
            "title": "Payments required",
            "hint": "For example, a fee to process an application or apply for a licence"
          }
        ],
        "next": [
          {
            "path": "/do-you-need-to-collect-the-location-of-land-or-premises-that-do-not-have-an-address"
          }
        ]
      },
      {
        "path": "/do-you-need-to-collect-documents-or-images-as-part-of-the-submission",
        "title": "Do you need to collect documents or images as part of the submission?",
        "components": [
          {
            "name": "ZjlaQC",
            "options": {},
            "schema": {},
            "type": "YesNoField",
            "title": "Documents and images collected",
            "hint": "For example, survey results, maps and assessments"
          }
        ],
        "next": [
          {
            "path": "/do-users-need-to-answer-a-set-of-repeating-questions"
          }
        ]
      },
      {
        "path": "/do-users-need-to-answer-a-set-of-repeating-questions",
        "title": "Do users need to answer a set of repeating questions?",
        "components": [
          {
            "name": "fvmVcF",
            "options": {},
            "schema": {},
            "type": "YesNoField",
            "title": "Repeated question sets required",
            "hint": "For example, to provide the make, model and description of a specified number of items"
          }
        ],
        "next": [
          {
            "path": "/will-the-form-need-to-calculate-answers-provided-by-the-user"
          }
        ]
      },
      {
        "path": "/do-you-have-an-existing-guide-on-govuk",
        "title": "Do you have an existing guide on GOV.UK?",
        "components": [
          {
            "name": "ZxksOp",
            "options": {},
            "schema": {},
            "type": "YesNoField",
            "title": "Existing GOV.UK guide",
            "values": {
              "type": "listRef"
            }
          }
        ],
        "next": [
          {
            "path": "/whats-the-link-for-the-existing-guide",
            "condition": "kONqxY"
          },
          {
            "path": "/do-you-have-a-deadline"
          }
        ]
      },
      {
        "path": "/whats-the-link-for-the-existing-guide",
        "title": "What's the link for the existing guide?",
        "components": [
          {
            "name": "TgRZwN",
            "options": {},
            "schema": {},
            "type": "TextField",
            "title": "Existing GOV.UK guide link"
          }
        ],
        "next": [
          {
            "path": "/do-you-have-a-deadline"
          }
        ]
      },
      {
        "path": "/do-you-have-a-deadline",
        "title": "Do you have a deadline?",
        "components": [
          {
            "name": "IQNUjZ",
            "options": {},
            "schema": {},
            "type": "YesNoField",
            "title": "Deadline required"
          }
        ],
        "next": [
          {
            "path": "/when-is-your-deadline",
            "condition": "ZsxitV"
          },
          {
            "path": "/how-long-does-your-form-need-to-be-available-on-govuk"
          }
        ]
      },
      {
        "path": "/when-is-your-deadline",
        "title": "When is your deadline?",
        "components": [
          {
            "name": "EsLGWL",
            "options": {},
            "schema": {},
            "type": "DatePartsField",
            "title": "Deadline date"
          }
        ],
        "next": [
          {
            "path": "/what-is-the-reason-for-your-deadline"
          }
        ]
      },
      {
        "path": "/what-is-the-reason-for-your-deadline",
        "title": "What is the reason for your deadline?",
        "components": [
          {
            "name": "xVmYmG",
            "options": {},
            "schema": {},
            "type": "MultilineTextField",
            "title": "Reason for deadline"
          }
        ],
        "next": [
          {
            "path": "/how-long-does-your-form-need-to-be-available-on-govuk"
          }
        ]
      },
      {
        "path": "/how-long-does-your-form-need-to-be-available-on-govuk",
        "title": "How long does your form need to be available on GOV.UK?",
        "components": [
          {
            "name": "rPWCXb",
            "options": {},
            "schema": {},
            "type": "RadiosField",
            "list": "gJIarM",
            "title": "Life of form",
            "values": {
              "type": "listRef"
            }
          }
        ],
        "next": [
          {
            "path": "/summary"
          }
        ]
      },
      {
        "path": "/will-you-be-the-owner-of-the-form",
        "title": "Will you be the owner of the form?",
        "components": [
          {
            "name": "lelgfW",
            "options": {},
            "schema": {},
            "type": "YesNoField",
            "title": "Form owner",
            "hint": "Every form must have an owner. Updates to a form must be approved by the form owner"
          }
        ],
        "next": [
          {
            "path": "/who-do-you-work-for",
            "condition": "oodwfD"
          },
          {
            "path": "/whats-the-name-of-the-form-owner",
            "condition": "cWGJtb"
          }
        ]
      },
      {
        "path": "/whats-the-name-of-the-form-owner",
        "title": "What's the name of the form owner?",
        "components": [
          {
            "name": "xXayGT",
            "options": {},
            "schema": {},
            "type": "TextField",
            "title": "Form owner name"
          }
        ],
        "next": [
          {
            "path": "/whats-the-email-address-of-the-form-owner"
          }
        ]
      },
      {
        "path": "/whats-the-email-address-of-the-form-owner",
        "title": "What's the email address of the form owner?",
        "components": [
          {
            "name": "KLUVzu",
            "options": {},
            "schema": {},
            "type": "EmailAddressField",
            "title": "Form owner email address"
          }
        ],
        "next": [
          {
            "path": "/who-do-you-work-for"
          }
        ]
      },
      {
        "path": "/will-the-form-need-to-calculate-answers-provided-by-the-user",
        "title": "Will the form need to calculate answers provided by the user?",
        "components": [
          {
            "name": "aFqOaH",
            "options": {},
            "schema": {},
            "type": "YesNoField",
            "title": "Calculations required",
            "hint": "For example, to add fees together or provide a total"
          }
        ],
        "next": [
          {
            "path": "/data-protection"
          }
        ]
      },
      {
        "path": "/do-you-need-to-collect-the-location-of-land-or-premises-that-do-not-have-an-address",
        "title": "Do you need to collect the location of land or premises that do not have an address?",
        "components": [
          {
            "name": "yHMOCZ",
            "options": {},
            "schema": {},
            "type": "YesNoField",
            "hint": "For example, fields or woodland",
            "title": "Location data required"
          }
        ],
        "next": [
          {
            "path": "/do-you-need-to-collect-documents-or-images-as-part-of-the-submission"
          }
        ]
      },
      {
        "path": "/data-protection",
        "title": "Data protection",
        "components": [
          {
            "name": "ZtVfWd",
            "options": {},
            "schema": {},
            "title": "Html",
            "type": "Html",
            "content": "<h2 class=\"govuk-heading-m\">For core Defra and the Animal and Plant Health Agency (APHA)</h2>\n\n<p class=\"govuk-body\">\nYou must complete the <a href=\"https://defra.sharepoint.com/sites/Defraintranet/SitePages/Data-Protection-Impact-Assessment.aspx\" class=\"govuk-link\" target=\"_blank\">data protection impact assessment (DPIA) screening questions (opens in new tab)</a>. They take less than 5 minutes to complete. \n<br><br>\nThe Data Protection team will assess if your processing of personal data is likely to result in a high risk to the rights and freedoms of individuals. If there’s a high risk, a DPIA is required by law. Most forms are unlikely to require a DPIA.\n<br><br>\nAll forms must have a privacy notice. If you do not have a privacy notice, the Defra Forms team will work with you to create one.\n</p>\n\n<h2 class=\"govuk-heading-m\">Other organisations</h2>\n\n<p class=\"govuk-body\">\nYou’ll need to contact your <a href=\"https://defra.sharepoint.com/sites/Defraintranet/SitePages/Data-protection.aspx#contact-us\" class=\"govuk-link\" target=\"_blank\">local Data Protection Team (opens in new tab)</a> if you work for:\n\n<ul class=\"govuk-list govuk-list--bullet\">\n<li>Natural England (NE)</li>\n<li>Rural Payments Agency (RPA)</li>\n<li>Environment Agency (EA)</li>\n<li>Veterinary Medicines Directorate (VMD)</li>\n<li>Centre for Environment, Fisheries and Aquaculture Science (Cefas)</li>\n<li>Joint Nature Conservation Committee (JNCC)</li>\n<li>Foresty Commission (FC)</li>\n<li>Marine Management Organisation (MMO)</li>\n</ul>\n</p>"
          },
          {
            "name": "wNEarp",
            "options": {},
            "schema": {},
            "type": "YesNoField",
            "title": "Have you completed the data protection impact assessment (DPIA) screening questions?"
          }
        ],
        "next": [
          {
            "path": "/do-you-have-an-existing-guide-on-govuk"
          }
        ]
      },
      {
        "path": "/where-to-send-form-submissions",
        "title": "Where to send form submissions",
        "components": [
          {
            "name": "PLZgUi",
            "title": "Html",
            "type": "Html",
            "content": "<p class=\"govuk-body\">\nWe send submitted forms by email to a nominated shared mailbox. \n<br><br>\nWe are exploring other output options such as saving submissions directly to SharePoint.\n<br><br>\nIf we can support your request for a from, we’ll ask you for more information about how you'll process the submissions at an exploration workshop.\n</p>",
            "options": {},
            "schema": {}
          },
          {
            "name": "JZVUWb",
            "title": "Do submissions need to be routed to different email addresses?",
            "type": "YesNoField",
            "hint": "",
            "options": {},
            "schema": {}
          }
        ],
        "next": [
          {
            "path": "/do-you-need-to-collect-a-payment"
          }
        ]
      },
      {
        "path": "/is-your-form-updated-frequently",
        "title": "Is your form updated frequently?",
        "components": [
          {
            "name": "SdiIlB",
            "title": "Form updated frequently",
            "type": "YesNoField",
            "hint": "",
            "options": {},
            "schema": {}
          }
        ],
        "next": [
          {
            "path": "/how-many-submissions-do-you-expect-to-receive-a-year"
          }
        ]
      }
    ],
    "conditions": [
      {
        "displayName": "yes - existing form",
        "name": "DkjIaR",
        "value": {
          "name": "yes - existing form",
          "conditions": [
            {
              "field": {
                "name": "mCZCyf",
                "type": "YesNoField",
                "display": "existing form"
              },
              "operator": "is",
              "value": {
                "type": "Value",
                "value": "true",
                "display": "true"
              }
            }
          ]
        }
      },
      {
        "displayName": "yes - until specific date",
        "name": "ZsxitV",
        "value": {
          "name": "yes - until specific date",
          "conditions": [
            {
              "field": {
                "name": "IQNUjZ",
                "type": "YesNoField",
                "display": "deadline"
              },
              "operator": "is",
              "value": {
                "type": "Value",
                "value": "true",
                "display": "true"
              }
            }
          ]
        }
      },
      {
        "displayName": "yes - has existing GOV.UK guidance",
        "name": "kONqxY",
        "value": {
          "name": "yes - has existing GOV.UK guidance",
          "conditions": [
            {
              "field": {
                "name": "ZxksOp",
                "type": "YesNoField",
                "display": "Existing GOV.UK guidance"
              },
              "operator": "is",
              "value": {
                "type": "Value",
                "value": "true",
                "display": "true"
              }
            }
          ]
        }
      },
      {
        "displayName": "No - form owner is different from person submitting request",
        "name": "cWGJtb",
        "value": {
          "name": "No - form owner is different from person submitting request",
          "conditions": [
            {
              "field": {
                "name": "lelgfW",
                "type": "YesNoField",
                "display": "Form owner"
              },
              "operator": "is",
              "value": {
                "type": "Value",
                "value": "false",
                "display": "false"
              }
            }
          ]
        }
      },
      {
        "displayName": "Yes - form owner is the same as person submitting request",
        "name": "oodwfD",
        "value": {
          "name": "Yes - form owner is the same as person submitting request",
          "conditions": [
            {
              "field": {
                "name": "lelgfW",
                "type": "YesNoField",
                "display": "Form owner"
              },
              "operator": "is",
              "value": {
                "type": "Value",
                "value": "true",
                "display": "true"
              }
            }
          ]
        }
      }
    ],
    "sections": [
      {
        "name": "section",
        "title": "Section title",
        "hideTitle": false
      }
    ],
    "lists": [
      {
        "title": "Organisations",
        "name": "hqocBW",
        "type": "string",
        "items": [
          {
            "text": "Department for Environment, Food and Rural Affairs (Defra)",
            "value": "Department for Environment, Food and Rural Affairs (Defra)"
          },
          {
            "text": "Animal and Plant Health Agency (APHA)",
            "value": "Animal and Plant Health Agency (APHA)"
          },
          {
            "text": "Natural England (NE)",
            "value": "Natural England (NE)"
          },
          {
            "text": "Forestry Commission (FC)",
            "value": "Forestry Commission (FC)"
          },
          {
            "text": "Centre for Environment Fisheries and Aquaculture Science (Cefas)",
            "value": "Centre for Environment Fisheries and Aquaculture Science (Cefas)"
          },
          {
            "text": "Veterinary Medicines Directorate (VMD)",
            "value": "Veterinary Medicines Directorate (VMD)"
          },
          {
            "text": "Environment Agency (EA)",
            "value": "Environment Agency (EA)"
          }
        ]
      },
      {
        "title": "Life of form",
        "name": "gJIarM",
        "type": "string",
        "items": [
          {
            "text": "Until a specific date",
            "value": "Set time frame"
          },
          {
            "text": "No time limit",
            "value": "No time limit"
          }
        ]
      },
      {
        "title": "Number of applications",
        "name": "UEnuwn",
        "type": "string",
        "items": [
          {
            "text": "Up to 50",
            "value": "Up to 50"
          },
          {
            "text": "51 to 250",
            "value": "51 to 250"
          },
          {
            "text": "251 to 10,000",
            "value": "251 to 10,000"
          },
          {
            "text": "10,001 to 100,000",
            "value": "10,001 to 100,000"
          },
          {
            "text": "More than 100,000",
            "value": "More than 100,000"
          }
        ]
      }
    ],
    "outputEmail": "defraforms@defra.gov.uk",
    "skipSummary": false,
    "startPage": "/what-is-your-name"
  },
  "live": {
    "name": "Request a form",
    "pages": [
      {
        "path": "/what-is-your-name",
        "title": "What is your name?",
        "components": [
          {
            "type": "TextField",
            "name": "textField",
            "title": "Name",
            "hint": "",
            "options": {},
            "schema": {}
          }
        ],
        "next": [
          {
            "path": "/what-is-your-email-address"
          }
        ]
      },
      {
        "title": "Summary",
        "path": "/summary",
        "controller": "./pages/summary.js",
        "components": [],
        "next": []
      },
      {
        "path": "/what-is-your-email-address",
        "title": "What is your email address?",
        "components": [
          {
            "name": "jwIhMa",
            "options": {},
            "schema": {},
            "type": "EmailAddressField",
            "title": "Email address"
          }
        ],
        "next": [
          {
            "path": "/will-you-be-the-owner-of-the-form"
          }
        ]
      },
      {
        "path": "/who-do-you-work-for",
        "title": "Who do you work for?",
        "components": [
          {
            "name": "NzsYde",
            "options": {},
            "schema": {},
            "type": "RadiosField",
            "title": "Your organisation",
            "list": "hqocBW",
            "values": {
              "type": "listRef"
            }
          }
        ],
        "next": [
          {
            "path": "/give-a-brief-description-of-your-service"
          }
        ]
      },
      {
        "path": "/give-a-brief-description-of-your-service",
        "title": "Give a brief description of your service",
        "components": [
          {
            "name": "drGlJl",
            "options": {},
            "schema": {},
            "type": "MultilineTextField",
            "title": "Description of your service"
          }
        ],
        "next": [
          {
            "path": "/do-you-have-an-existing-form"
          }
        ]
      },
      {
        "path": "/do-you-have-an-existing-form",
        "title": "Do you have an existing form?",
        "components": [
          {
            "name": "mCZCyf",
            "options": {},
            "schema": {},
            "type": "YesNoField",
            "title": "Existing form",
            "hint": "This can be an existing paper-based form, for example, a PDF or Microsoft Word document"
          }
        ],
        "next": [
          {
            "path": "/what-is-the-link-to-the-form-IyRbdG",
            "condition": "DkjIaR"
          },
          {
            "path": "/how-many-submissions-do-you-expect-to-receive-a-year"
          }
        ]
      },
      {
        "path": "/what-is-the-link-to-the-form-IyRbdG",
        "title": "What is the link to the form?",
        "components": [
          {
            "name": "ssTfVS",
            "options": {},
            "schema": {},
            "type": "TextField",
            "title": "Link for existing form"
          }
        ],
        "next": [
          {
            "path": "/is-your-form-updated-frequently"
          }
        ]
      },
      {
        "path": "/how-many-submissions-do-you-expect-to-receive-a-year",
        "title": "How many submissions do you expect to receive a year?",
        "components": [
          {
            "name": "IeDmsh",
            "options": {},
            "schema": {},
            "type": "RadiosField",
            "hint": "This will help us to provide you with a solution that meets your requirements",
            "title": "Number of annual applications",
            "list": "UEnuwn"
          }
        ],
        "next": [
          {
            "path": "/where-to-send-form-submissions"
          }
        ]
      },
      {
        "path": "/do-you-need-to-collect-a-payment",
        "title": "Do you need to collect a payment?",
        "components": [
          {
            "name": "AAWpzq",
            "options": {},
            "schema": {},
            "type": "YesNoField",
            "title": "Payments required",
            "hint": "For example, a fee to process an application or apply for a licence"
          }
        ],
        "next": [
          {
            "path": "/do-you-need-to-collect-the-location-of-land-or-premises-that-do-not-have-an-address"
          }
        ]
      },
      {
        "path": "/do-you-need-to-collect-documents-or-images-as-part-of-the-submission",
        "title": "Do you need to collect documents or images as part of the submission?",
        "components": [
          {
            "name": "ZjlaQC",
            "options": {},
            "schema": {},
            "type": "YesNoField",
            "title": "Documents and images collected",
            "hint": "For example, survey results, maps and assessments"
          }
        ],
        "next": [
          {
            "path": "/do-users-need-to-answer-a-set-of-repeating-questions"
          }
        ]
      },
      {
        "path": "/do-users-need-to-answer-a-set-of-repeating-questions",
        "title": "Do users need to answer a set of repeating questions?",
        "components": [
          {
            "name": "fvmVcF",
            "options": {},
            "schema": {},
            "type": "YesNoField",
            "title": "Repeated question sets required",
            "hint": "For example, to provide the make, model and description of a specified number of items"
          }
        ],
        "next": [
          {
            "path": "/will-the-form-need-to-calculate-answers-provided-by-the-user"
          }
        ]
      },
      {
        "path": "/do-you-have-an-existing-guide-on-govuk",
        "title": "Do you have an existing guide on GOV.UK?",
        "components": [
          {
            "name": "ZxksOp",
            "options": {},
            "schema": {},
            "type": "YesNoField",
            "title": "Existing GOV.UK guide",
            "values": {
              "type": "listRef"
            }
          }
        ],
        "next": [
          {
            "path": "/whats-the-link-for-the-existing-guide",
            "condition": "kONqxY"
          },
          {
            "path": "/do-you-have-a-deadline"
          }
        ]
      },
      {
        "path": "/whats-the-link-for-the-existing-guide",
        "title": "What's the link for the existing guide?",
        "components": [
          {
            "name": "TgRZwN",
            "options": {},
            "schema": {},
            "type": "TextField",
            "title": "Existing GOV.UK guide link"
          }
        ],
        "next": [
          {
            "path": "/do-you-have-a-deadline"
          }
        ]
      },
      {
        "path": "/do-you-have-a-deadline",
        "title": "Do you have a deadline?",
        "components": [
          {
            "name": "IQNUjZ",
            "options": {},
            "schema": {},
            "type": "YesNoField",
            "title": "Deadline required"
          }
        ],
        "next": [
          {
            "path": "/when-is-your-deadline",
            "condition": "ZsxitV"
          },
          {
            "path": "/how-long-does-your-form-need-to-be-available-on-govuk"
          }
        ]
      },
      {
        "path": "/when-is-your-deadline",
        "title": "When is your deadline?",
        "components": [
          {
            "name": "EsLGWL",
            "options": {},
            "schema": {},
            "type": "DatePartsField",
            "title": "Deadline date"
          }
        ],
        "next": [
          {
            "path": "/what-is-the-reason-for-your-deadline"
          }
        ]
      },
      {
        "path": "/what-is-the-reason-for-your-deadline",
        "title": "What is the reason for your deadline?",
        "components": [
          {
            "name": "xVmYmG",
            "options": {},
            "schema": {},
            "type": "MultilineTextField",
            "title": "Reason for deadline"
          }
        ],
        "next": [
          {
            "path": "/how-long-does-your-form-need-to-be-available-on-govuk"
          }
        ]
      },
      {
        "path": "/how-long-does-your-form-need-to-be-available-on-govuk",
        "title": "How long does your form need to be available on GOV.UK?",
        "components": [
          {
            "name": "rPWCXb",
            "options": {},
            "schema": {},
            "type": "RadiosField",
            "list": "gJIarM",
            "title": "Life of form",
            "values": {
              "type": "listRef"
            }
          }
        ],
        "next": [
          {
            "path": "/summary"
          }
        ]
      },
      {
        "path": "/will-you-be-the-owner-of-the-form",
        "title": "Will you be the owner of the form?",
        "components": [
          {
            "name": "lelgfW",
            "options": {},
            "schema": {},
            "type": "YesNoField",
            "title": "Form owner",
            "hint": "Every form must have an owner. Updates to a form must be approved by the form owner"
          }
        ],
        "next": [
          {
            "path": "/who-do-you-work-for",
            "condition": "oodwfD"
          },
          {
            "path": "/whats-the-name-of-the-form-owner",
            "condition": "cWGJtb"
          }
        ]
      },
      {
        "path": "/whats-the-name-of-the-form-owner",
        "title": "What's the name of the form owner?",
        "components": [
          {
            "name": "xXayGT",
            "options": {},
            "schema": {},
            "type": "TextField",
            "title": "Form owner name"
          }
        ],
        "next": [
          {
            "path": "/whats-the-email-address-of-the-form-owner"
          }
        ]
      },
      {
        "path": "/whats-the-email-address-of-the-form-owner",
        "title": "What's the email address of the form owner?",
        "components": [
          {
            "name": "KLUVzu",
            "options": {},
            "schema": {},
            "type": "EmailAddressField",
            "title": "Form owner email address"
          }
        ],
        "next": [
          {
            "path": "/who-do-you-work-for"
          }
        ]
      },
      {
        "path": "/will-the-form-need-to-calculate-answers-provided-by-the-user",
        "title": "Will the form need to calculate answers provided by the user?",
        "components": [
          {
            "name": "aFqOaH",
            "options": {},
            "schema": {},
            "type": "YesNoField",
            "title": "Calculations required",
            "hint": "For example, to add fees together or provide a total"
          }
        ],
        "next": [
          {
            "path": "/data-protection"
          }
        ]
      },
      {
        "path": "/do-you-need-to-collect-the-location-of-land-or-premises-that-do-not-have-an-address",
        "title": "Do you need to collect the location of land or premises that do not have an address?",
        "components": [
          {
            "name": "yHMOCZ",
            "options": {},
            "schema": {},
            "type": "YesNoField",
            "hint": "For example, fields or woodland",
            "title": "Location data required"
          }
        ],
        "next": [
          {
            "path": "/do-you-need-to-collect-documents-or-images-as-part-of-the-submission"
          }
        ]
      },
      {
        "path": "/data-protection",
        "title": "Data protection",
        "components": [
          {
            "name": "ZtVfWd",
            "options": {},
            "schema": {},
            "title": "Html",
            "type": "Html",
            "content": "<h2 class=\"govuk-heading-m\">For core Defra and the Animal and Plant Health Agency (APHA)</h2>\n\n<p class=\"govuk-body\">\nYou must complete the <a href=\"https://defra.sharepoint.com/sites/Defraintranet/SitePages/Data-Protection-Impact-Assessment.aspx\" class=\"govuk-link\" target=\"_blank\">data protection impact assessment (DPIA) screening questions (opens in new tab)</a>. They take less than 5 minutes to complete. \n<br><br>\nThe Data Protection team will assess if your processing of personal data is likely to result in a high risk to the rights and freedoms of individuals. If there’s a high risk, a DPIA is required by law. Most forms are unlikely to require a DPIA.\n<br><br>\nAll forms must have a privacy notice. If you do not have a privacy notice, the Defra Forms team will work with you to create one.\n</p>\n\n<h2 class=\"govuk-heading-m\">Other organisations</h2>\n\n<p class=\"govuk-body\">\nYou’ll need to contact your <a href=\"https://defra.sharepoint.com/sites/Defraintranet/SitePages/Data-protection.aspx#contact-us\" class=\"govuk-link\" target=\"_blank\">local Data Protection Team (opens in new tab)</a> if you work for:\n\n<ul class=\"govuk-list govuk-list--bullet\">\n<li>Natural England (NE)</li>\n<li>Rural Payments Agency (RPA)</li>\n<li>Environment Agency (EA)</li>\n<li>Veterinary Medicines Directorate (VMD)</li>\n<li>Centre for Environment, Fisheries and Aquaculture Science (Cefas)</li>\n<li>Joint Nature Conservation Committee (JNCC)</li>\n<li>Foresty Commission (FC)</li>\n<li>Marine Management Organisation (MMO)</li>\n</ul>\n</p>"
          },
          {
            "name": "wNEarp",
            "options": {},
            "schema": {},
            "type": "YesNoField",
            "title": "Have you completed the data protection impact assessment (DPIA) screening questions?"
          }
        ],
        "next": [
          {
            "path": "/do-you-have-an-existing-guide-on-govuk"
          }
        ]
      },
      {
        "path": "/where-to-send-form-submissions",
        "title": "Where to send form submissions",
        "components": [
          {
            "name": "PLZgUi",
            "title": "Html",
            "type": "Html",
            "content": "<p class=\"govuk-body\">\nWe send submitted forms by email to a nominated shared mailbox. \n<br><br>\nWe are exploring other output options such as saving submissions directly to SharePoint.\n<br><br>\nIf we can support your request for a from, we’ll ask you for more information about how you'll process the submissions at an exploration workshop.\n</p>",
            "options": {},
            "schema": {}
          },
          {
            "name": "JZVUWb",
            "title": "Do submissions need to be routed to different email addresses?",
            "type": "YesNoField",
            "hint": "",
            "options": {},
            "schema": {}
          }
        ],
        "next": [
          {
            "path": "/do-you-need-to-collect-a-payment"
          }
        ]
      },
      {
        "path": "/is-your-form-updated-frequently",
        "title": "Is your form updated frequently?",
        "components": [
          {
            "name": "SdiIlB",
            "title": "Form updated frequently",
            "type": "YesNoField",
            "hint": "",
            "options": {},
            "schema": {}
          }
        ],
        "next": [
          {
            "path": "/how-many-submissions-do-you-expect-to-receive-a-year"
          }
        ]
      }
    ],
    "conditions": [
      {
        "displayName": "yes - existing form",
        "name": "DkjIaR",
        "value": {
          "name": "yes - existing form",
          "conditions": [
            {
              "field": {
                "name": "mCZCyf",
                "type": "YesNoField",
                "display": "existing form"
              },
              "operator": "is",
              "value": {
                "type": "Value",
                "value": "true",
                "display": "true"
              }
            }
          ]
        }
      },
      {
        "displayName": "yes - until specific date",
        "name": "ZsxitV",
        "value": {
          "name": "yes - until specific date",
          "conditions": [
            {
              "field": {
                "name": "IQNUjZ",
                "type": "YesNoField",
                "display": "deadline"
              },
              "operator": "is",
              "value": {
                "type": "Value",
                "value": "true",
                "display": "true"
              }
            }
          ]
        }
      },
      {
        "displayName": "yes - has existing GOV.UK guidance",
        "name": "kONqxY",
        "value": {
          "name": "yes - has existing GOV.UK guidance",
          "conditions": [
            {
              "field": {
                "name": "ZxksOp",
                "type": "YesNoField",
                "display": "Existing GOV.UK guidance"
              },
              "operator": "is",
              "value": {
                "type": "Value",
                "value": "true",
                "display": "true"
              }
            }
          ]
        }
      },
      {
        "displayName": "No - form owner is different from person submitting request",
        "name": "cWGJtb",
        "value": {
          "name": "No - form owner is different from person submitting request",
          "conditions": [
            {
              "field": {
                "name": "lelgfW",
                "type": "YesNoField",
                "display": "Form owner"
              },
              "operator": "is",
              "value": {
                "type": "Value",
                "value": "false",
                "display": "false"
              }
            }
          ]
        }
      },
      {
        "displayName": "Yes - form owner is the same as person submitting request",
        "name": "oodwfD",
        "value": {
          "name": "Yes - form owner is the same as person submitting request",
          "conditions": [
            {
              "field": {
                "name": "lelgfW",
                "type": "YesNoField",
                "display": "Form owner"
              },
              "operator": "is",
              "value": {
                "type": "Value",
                "value": "true",
                "display": "true"
              }
            }
          ]
        }
      }
    ],
    "sections": [
      {
        "name": "section",
        "title": "Section title",
        "hideTitle": false
      }
    ],
    "lists": [
      {
        "title": "Organisations",
        "name": "hqocBW",
        "type": "string",
        "items": [
          {
            "text": "Department for Environment, Food and Rural Affairs (Defra)",
            "value": "Department for Environment, Food and Rural Affairs (Defra)"
          },
          {
            "text": "Animal and Plant Health Agency (APHA)",
            "value": "Animal and Plant Health Agency (APHA)"
          },
          {
            "text": "Natural England (NE)",
            "value": "Natural England (NE)"
          },
          {
            "text": "Forestry Commission (FC)",
            "value": "Forestry Commission (FC)"
          },
          {
            "text": "Centre for Environment Fisheries and Aquaculture Science (Cefas)",
            "value": "Centre for Environment Fisheries and Aquaculture Science (Cefas)"
          },
          {
            "text": "Veterinary Medicines Directorate (VMD)",
            "value": "Veterinary Medicines Directorate (VMD)"
          },
          {
            "text": "Environment Agency (EA)",
            "value": "Environment Agency (EA)"
          }
        ]
      },
      {
        "title": "Life of form",
        "name": "gJIarM",
        "type": "string",
        "items": [
          {
            "text": "Until a specific date",
            "value": "Set time frame"
          },
          {
            "text": "No time limit",
            "value": "No time limit"
          }
        ]
      },
      {
        "title": "Number of applications",
        "name": "UEnuwn",
        "type": "string",
        "items": [
          {
            "text": "Up to 50",
            "value": "Up to 50"
          },
          {
            "text": "51 to 250",
            "value": "51 to 250"
          },
          {
            "text": "251 to 10,000",
            "value": "251 to 10,000"
          },
          {
            "text": "10,001 to 100,000",
            "value": "10,001 to 100,000"
          },
          {
            "text": "More than 100,000",
            "value": "More than 100,000"
          }
        ]
      }
    ],
    "outputEmail": "defraforms@defra.gov.uk",
    "skipSummary": false,
    "startPage": "/what-is-your-name"
  }
}